{"_index":".kibana","_type":"dashboard","_id":"a10ea000-5be8-11e7-878e-17ed0a725bef","_version":3,"found":true,"_source":{"title":"template","hits":0,"description":"","panelsJSON":"[{\"col\":1,\"columns\":[\"_source\"],\"id\":\"mni94x9z4sb7of0\",\"panelIndex\":1,\"row\":12,\"size_x\":12,\"size_y\":14,\"sort\":[\"@timestamp\",\"desc\"],\"type\":\"search\"},{\"col\":1,\"id\":\"1a146350-5bed-11e7-878e-17ed0a725bef\",\"panelIndex\":4,\"row\":1,\"size_x\":12,\"size_y\":2,\"type\":\"visualization\"},{\"col\":1,\"id\":\"d0036750-5d6a-11e7-90be-d7222f44c470\",\"panelIndex\":5,\"row\":3,\"size_x\":12,\"size_y\":3,\"type\":\"visualization\"},{\"col\":4,\"id\":\"9ba4e100-5d6a-11e7-90be-d7222f44c470\",\"panelIndex\":6,\"row\":6,\"size_x\":5,\"size_y\":3,\"type\":\"visualization\"},{\"col\":9,\"id\":\"9605a780-5d96-11e7-bde6-ff6869edc834\",\"panelIndex\":7,\"row\":6,\"size_x\":4,\"size_y\":3,\"type\":\"visualization\"},{\"col\":4,\"id\":\"09e4f290-b270-11e7-916c-c700f2e46f5b\",\"panelIndex\":8,\"row\":9,\"size_x\":3,\"size_y\":3,\"type\":\"visualization\"},{\"col\":7,\"id\":\"337d1980-b26f-11e7-916c-c700f2e46f5b\",\"panelIndex\":9,\"row\":9,\"size_x\":6,\"size_y\":3,\"type\":\"visualization\"},{\"size_x\":3,\"size_y\":3,\"panelIndex\":10,\"type\":\"visualization\",\"id\":\"6aae7970-b270-11e7-916b-3367c2b988c6\",\"col\":1,\"row\":6},{\"size_x\":3,\"size_y\":3,\"panelIndex\":11,\"type\":\"visualization\",\"id\":\"732ab730-b270-11e7-916b-3367c2b988c6\",\"col\":1,\"row\":9}]","optionsJSON":"{\"darkTheme\":true}","uiStateJSON":"{\"P-2\":{\"vis\":{\"legendOpen\":true}},\"P-3\":{\"vis\":{\"legendOpen\":false}},\"P-5\":{\"vis\":{\"legendOpen\":false}},\"P-6\":{\"vis\":{\"legendOpen\":true}},\"P-7\":{\"spy\":{\"mode\":{\"fill\":false,\"name\":null}}}}","version":1,"timeRestore":false,"kibanaSavedObjectMeta":{"searchSourceJSON":"{\"filter\":[{\"query\":{\"query_string\":{\"analyze_wildcard\":true,\"query\":\"*\"}}}]}"}}}